{
  "project_info": {
    "project_number": "936042723281",
    "project_id": "smartfarm-160409"
  },
  "client": [
    {
      "client_info": {
        "mobilesdk_app_id": "1:936042723281:android:54b7ed2a23601773",
        "android_client_info": {
          "package_name": "smartfarm.team.smartfarmapp"
        }
      },
      "oauth_client": [],
      "api_key": [
        {
          "current_key": "AIzaSyDiWlJFFoq4UPbp0n1XxhvpyXR5YpsvIxc"
        }
      ],
      "services": {
        "analytics_service": {
          "status": 1
        },
        "appinvite_service": {
          "status": 1,
          "other_platform_oauth_client": []
        },
        "ads_service": {
          "status": 1
        }
      }
    }
  ],
  "configuration_version": "1"
}